fintalk_logger/__init__.py
fintalk_logger/logger.py
fintalk_logger/models/__init__.py
fintalk_logger/models/basemodels.py
fintalk_logger/utils/__init__.py
fintalk_logger/utils/get_http.py
fintalk_logger/utils/get_ip.py
fintalk_logger/utils/get_request_id.py
fintalk_logger/utils/get_user.py
fintalk_logger/utils/remove_empty_keys.py
fintalk_logger-0.0.12.dist-info/LICENSE
fintalk_logger-0.0.12.dist-info/METADATA
fintalk_logger-0.0.12.dist-info/WHEEL
fintalk_logger-0.0.12.dist-info/top_level.txt
fintalk_logger-0.0.12.dist-info/RECORD
