Metadata-Version: 2.1
Name: fintalk_logger
Version: 0.0.12
Summary: Fintalk Python logger
Author: fintalk
Classifier: Programming Language :: Python :: 3
Classifier: License :: OSI Approved :: MIT License
Classifier: Operating System :: OS Independent
Requires-Python: >=3.8
License-File: LICENSE
Requires-Dist: requests
Requires-Dist: pydantic
Requires-Dist: loguru
